{"cameraMode":{"drawMode":0,"name":"Shaded","section":"Shading Mode"},"sceneLighting":false,"audioPlay":false,"sceneViewState":{"m_AlwaysRefresh":false,"showFog":true,"showSkybox":false,"showFlares":true,"showImageEffects":true,"showParticleSystems":true,"showVisualEffectGraphs":true,"m_FxEnabled":true},"in2DMode":false,"pivot":{"x":129.073974609375,"y":8.969457626342774,"z":-9.459784507751465},"rotation":{"x":-0.004817921668291092,"y":-0.9951426386833191,"z":0.0486639030277729,"w":-0.08800055086612702},"size":16.596418380737306,"orthographic":false}